{
  "rooms": [
    {
      "id": "r1",
      "type": "entry",
      "neighbors": ["r2"]
    },
    {
      "id": "r2",
      "type": "combat",
      "neighbors": ["r1", "r3"],
      "encounterTable": "weak"
    },
    {
      "id": "r3",
      "type": "shard",
      "neighbors": ["r2", "r4"],
      "encounterTable": "mid",
      "shardId": "shard1",
      "guardEncounter": "guard_watch"
    },
    {
      "id": "r4",
      "type": "combat",
      "neighbors": ["r3", "r5"],
      "encounterTable": "mid"
    },
    {
      "id": "r5",
      "type": "shard",
      "neighbors": ["r4", "r6"],
      "encounterTable": "mid",
      "shardId": "shard2",
      "guardEncounter": "guard1"
    },
    {
      "id": "r6",
      "type": "combat",
      "neighbors": ["r5", "r7"],
      "encounterTable": "mid"
    },
    {
      "id": "r7",
      "type": "shard",
      "neighbors": ["r6", "r8"],
      "encounterTable": "hard",
      "shardId": "shard3",
      "guardEncounter": "guard2"
    },
    {
      "id": "r8",
      "type": "combat",
      "neighbors": ["r7", "r9"],
      "encounterTable": "hard"
    },
    {
      "id": "r9",
      "type": "shard",
      "neighbors": ["r8", "r10"],
      "encounterTable": "hard",
      "shardId": "shard4",
      "guardEncounter": "guard3"
    },
    {
      "id": "r10",
      "type": "combat",
      "neighbors": ["r9", "boss"],
      "encounterTable": "hard",
      "guardEncounter": "guard_royal"
    },
    {
      "id": "boss",
      "type": "boss",
      "neighbors": ["r10"]
    }
  ],
  "bossEncounterId": "boss_fear"
}
